{
  "unversionedId": "ONDC_API",
  "id": "ONDC_API",
  "title": "ONDC API",
  "description": "ONDC API acting as a Gateway of buyer and seller. The ONDC get the request of the buyer and send it to the seller . Get the seller response details forewarded to buyer.",
  "source": "@site/docs/ONDC_API.md",
  "sourceDirName": ".",
  "slug": "/ONDC_API",
  "permalink": "/docs/ONDC_API",
  "draft": false,
  "editUrl": "https://github.com/facebook/docusaurus/tree/main/packages/create-docusaurus/templates/shared/docs/ONDC_API.md",
  "tags": [],
  "version": "current",
  "sidebarPosition": 2,
  "frontMatter": {
    "sidebar_position": 2
  },
  "sidebar": "tutorialSidebar",
  "previous": {
    "title": "Care Commerce",
    "permalink": "/docs/Overiview/Overview-0f-Care-Commerce"
  },
  "next": {
    "title": "Care Commere Store API",
    "permalink": "/docs/category/care-commere-store-api"
  }
}